AUTHORS.rst
CONTRIBUTING.rst
HISTORY.rst
LICENSE
MANIFEST.in
README.rst
setup.cfg
setup.py
django_money_rates_nb.egg-info/PKG-INFO
django_money_rates_nb.egg-info/SOURCES.txt
django_money_rates_nb.egg-info/dependency_links.txt
django_money_rates_nb.egg-info/not-zip-safe
django_money_rates_nb.egg-info/requires.txt
django_money_rates_nb.egg-info/top_level.txt
djmoney_rates/__init__.py
djmoney_rates/admin.py
djmoney_rates/backends.py
djmoney_rates/exceptions.py
djmoney_rates/models.py
djmoney_rates/settings.py
djmoney_rates/utils.py
djmoney_rates/management/__init__.py
djmoney_rates/management/commands/__init__.py
djmoney_rates/management/commands/update_rates.py
djmoney_rates/migrations/0001_initial.py
djmoney_rates/migrations/__init__.py
tests/__init__.py
tests/settings.py
tests/test_backends.py
tests/test_commands.py
tests/test_utils.py